{
	"configurations" : 
	[
		{
			"directories" : 
			[
				{
					"build" : ".",
					"jsonFile" : "directory-.-Debug-d0094a50bb2071803777.json",
					"minimumCMakeVersion" : 
					{
						"string" : "3.22"
					},
					"projectIndex" : 0,
					"source" : ".",
					"targetIndexes" : 
					[
						0
					]
				}
			],
			"name" : "Debug",
			"projects" : 
			[
				{
					"directoryIndexes" : 
					[
						0
					],
					"name" : "wait",
					"targetIndexes" : 
					[
						0
					]
				}
			],
			"targets" : 
			[
				{
					"directoryIndex" : 0,
					"id" : "wait::@6890427a1f51a3e7e1df",
					"jsonFile" : "target-wait-Debug-26f9c1b0c8285a9caf1b.json",
					"name" : "wait",
					"projectIndex" : 0
				}
			]
		}
	],
	"kind" : "codemodel",
	"paths" : 
	{
		"build" : "D:/SLAM/code/week_05/wait/cmake-build-debug",
		"source" : "D:/SLAM/code/week_05/wait"
	},
	"version" : 
	{
		"major" : 2,
		"minor" : 3
	}
}
